{"status":"done","publicPath":"/","chunks":{"about":[{"name":"js/about.js","publicPath":"/js/about.js","path":"/home/olusia/inzynierka/frontend/dist/js/about.js"}],"app":[{"name":"js/app.js","publicPath":"/js/app.js","path":"/home/olusia/inzynierka/frontend/dist/js/app.js"},{"name":"app.dcf7d05745a5aa5b4a4c.hot-update.js","publicPath":"/app.dcf7d05745a5aa5b4a4c.hot-update.js","path":"/home/olusia/inzynierka/frontend/dist/app.dcf7d05745a5aa5b4a4c.hot-update.js"}]},"error":"ModuleError","message":"Module Error (from ./node_modules/eslint-loader/index.js):\nerror: Missing trailing comma (comma-dangle) at src/components/VisitDiagnosisCard.vue:59:16:\n  57 |       } = this;\n  58 |       const data = {\n> 59 |         results\n     |                ^\n  60 |       };\n  61 |         // const { id } = this.$route.params;\n  62 |       const token = localStorage.getItem('token');\n\n\n1 error found.\n1 error potentially fixable with the `--fix` option."}