{"status":"done","publicPath":"/","chunks":{"about":[{"name":"js/about.js","publicPath":"/js/about.js","path":"/home/olusia/inzynierka/frontend/dist/js/about.js"}],"app":[{"name":"js/app.js","publicPath":"/js/app.js","path":"/home/olusia/inzynierka/frontend/dist/js/app.js"},{"name":"app.73514c61453eaecd996b.hot-update.js","publicPath":"/app.73514c61453eaecd996b.hot-update.js","path":"/home/olusia/inzynierka/frontend/dist/app.73514c61453eaecd996b.hot-update.js"}]},"error":"ModuleError","message":"Module Error (from ./node_modules/eslint-loader/index.js):\nerror: Trailing spaces not allowed (no-trailing-spaces) at src/views/Home.vue:32:1:\n  30 |   }\n  31 |   p {\n> 32 |     \n     | ^\n  33 |   }\n  34 |   .nav {\n  35 |     padding: 30px;\n\n\n1 error found.\n1 error potentially fixable with the `--fix` option."}